jumpstarter_driver_yepkit/__init__.py
jumpstarter_driver_yepkit/conftest.py
jumpstarter_driver_yepkit/driver.py
jumpstarter_driver_yepkit/driver_test.py
jumpstarter_driver_yepkit/py.typed
jumpstarter_driver_yepkit-0.7.4.dist-info/METADATA
jumpstarter_driver_yepkit-0.7.4.dist-info/WHEEL
jumpstarter_driver_yepkit-0.7.4.dist-info/entry_points.txt
jumpstarter_driver_yepkit-0.7.4.dist-info/RECORD
